server/__init__.py
server/server.py
server/common/__init__.py
server/common/custom_decorators.py
server/common/descriptors.py
server/common/errors.py
server/common/metaclasses.py
server/common/utils.py
server/common/variables.py
server/logs/__init__.py
server/logs/config_client_log.py
server/logs/config_server_log.py
server/server/__init__.py
server/server/add_user.py
server/server/config_window.py
server/server/core.py
server/server/database.py
server/server/main_window.py
server/server/remove_user.py
server/server/stat_window.py
server/tests/__init__.py
server/tests/test_client.py
server/tests/test_server.py
server/tests/test_utils.py
megaLexa_server_messenger-1.1.0.dist-info/METADATA
megaLexa_server_messenger-1.1.0.dist-info/WHEEL
megaLexa_server_messenger-1.1.0.dist-info/top_level.txt
megaLexa_server_messenger-1.1.0.dist-info/RECORD
