Metadata-Version: 2.1
Name: megaLexa-server-messenger
Version: 1.1.0
Summary: megaLexa_server_messenger
Home-page: UNKNOWN
Author: MegaLexa
Author-email: itsnotmyrealmail@mail.ru
License: UNKNOWN
Platform: UNKNOWN
Requires-Dist: PyQt5
Requires-Dist: sqlalchemy
Requires-Dist: pycryptodome
Requires-Dist: pycryptodomex
